guro/__init__.py
guro/cli/__init__.py
guro/cli/main.py
guro/core/__init__.py
guro/core/benchmark.py
guro/core/heatmap.py
guro/core/monitor.py
guro-1.0.3.dist-info/LICENSE
guro-1.0.3.dist-info/METADATA
guro-1.0.3.dist-info/WHEEL
guro-1.0.3.dist-info/entry_points.txt
guro-1.0.3.dist-info/top_level.txt
guro-1.0.3.dist-info/RECORD
